client/__init__.py
client/client.py
client/client/__init__.py
client/client/add_contact.py
client/client/client_db.py
client/client/del_contact.py
client/client/main_window.py
client/client/main_window_conv.py
client/client/start_dialog.py
client/client/transport.py
client/client/logs/__init__.py
client/client/logs/client_log_config.py
client/common/__init__.py
client/common/descriptors.py
client/common/errors.py
client/common/metaclasses.py
client/common/proj_decorators.py
client/common/utils.py
client/common/variables.py
client/unit_tests/__init__.py
client/unit_tests/test_utils.py
MsgJimPyClient-1.1.3.dist-info/METADATA
MsgJimPyClient-1.1.3.dist-info/WHEEL
MsgJimPyClient-1.1.3.dist-info/top_level.txt
MsgJimPyClient-1.1.3.dist-info/RECORD
