Metadata-Version: 2.1
Name: MsgJimPyClient
Version: 1.1.3
Summary: Client part of jim based messenger 
Author: Roman Lopatin
Author-email: romanlopatin@gmail.com
Requires-Dist: PyQt5
Requires-Dist: sqlalchemy
